gwlab_viterbi_python/__init__.py
gwlab_viterbi_python/exceptions.py
gwlab_viterbi_python/gwlab_viterbi.py
gwlab_viterbi_python/inputs.py
gwlab_viterbi_python/settings.py
gwlab_viterbi_python/tests/__init__.py
gwlab_viterbi_python/tests/test_gwlab_viterbi_python.py
gwlab_viterbi_python/tests/test_viterbi_job.py
gwlab_viterbi_python/utils/__init__.py
gwlab_viterbi_python/utils/file_download.py
gwlab_viterbi_python/utils/file_filters.py
gwlab_viterbi_python/utils/identifiers.py
gwlab_viterbi_python/utils/tests/__init__.py
gwlab_viterbi_python/utils/tests/test_file_download.py
gwlab_viterbi_python/utils/tests/test_file_filters.py
gwlab_viterbi_python/utils/tests/test_identifiers.py
gwlab_viterbi_python/viterbi_job.py
gwlab_viterbi_python-0.2.3.dist-info/LICENSE
gwlab_viterbi_python-0.2.3.dist-info/METADATA
gwlab_viterbi_python-0.2.3.dist-info/WHEEL
gwlab_viterbi_python-0.2.3.dist-info/RECORD
